odoo8_addon_medical_patient_occupation-8.0.1.1.0.99.dev3-py2.7-nspkg.pth
odoo_addons/medical_patient_occupation/__openerp__.py
odoo_addons/medical_patient_occupation/__init__.py
odoo_addons/medical_patient_occupation/README.rst
odoo_addons/medical_patient_occupation/security/ir.model.access.csv
odoo_addons/medical_patient_occupation/models/medical_patient.py
odoo_addons/medical_patient_occupation/models/__init__.py
odoo_addons/medical_patient_occupation/models/medical_patient_occupation.py
odoo_addons/medical_patient_occupation/i18n/pt_BR.po
odoo_addons/medical_patient_occupation/views/medical_patient_occupation_view.xml
odoo_addons/medical_patient_occupation/views/medical_patient_view.xml
odoo8_addon_medical_patient_occupation-8.0.1.1.0.99.dev3.dist-info/top_level.txt
odoo8_addon_medical_patient_occupation-8.0.1.1.0.99.dev3.dist-info/WHEEL
odoo8_addon_medical_patient_occupation-8.0.1.1.0.99.dev3.dist-info/RECORD
odoo8_addon_medical_patient_occupation-8.0.1.1.0.99.dev3.dist-info/metadata.json
odoo8_addon_medical_patient_occupation-8.0.1.1.0.99.dev3.dist-info/DESCRIPTION.rst
odoo8_addon_medical_patient_occupation-8.0.1.1.0.99.dev3.dist-info/METADATA
odoo8_addon_medical_patient_occupation-8.0.1.1.0.99.dev3.dist-info/namespace_packages.txt
